
[
  {
    "imgUrl": "https://my.ispl-t10.com/assets/img/media/paper4.jpg",
    "altText": "Pudhari",
    "title": "Pudhari",
    "date": "February 26, 2024"
  },
  { 
    "imgUrl": "https://my.ispl-t10.com/assets/img/media/paper1.jpg",
    "altText": "Daily Excelsior",
    "title": "Daily Excelsior",
    "date": "February 26, 2024"
  },
  {
    "imgUrl": "https://my.ispl-t10.com/assets/img/media/paper2.jpg",
    "altText": "Mid-Day",
    "title": "Mid-Day",
    "date": "February 26, 2024"
  },
  {
    "imgUrl": "https://my.ispl-t10.com/assets/img/media/paper3.jpg",
    "altText": "Hindustan Times",
    "title": "Hindustan Times",
    "date": "February 26, 2024"
  },
  {
    "imgUrl": "https://my.ispl-t10.com/assets/img/media/paper101.png",
    "altText": "Mid-Day",
    "title": "Mid-Day",
    "date": "August 19, 2024"
  },
  {
    "imgUrl": "https://my.ispl-t10.com/assets/img/media/paper102.png",
    "altText": "Hindustan Times",
    "title": "Hindustan Times",
    "date": "August 19, 2024"
  },
  {
    "imgUrl": "https://my.ispl-t10.com/assets/img/media/paper103.png",
    "altText": "Dainik jagran",
    "title": "Dainik jagran",
    "date": "August 20, 2024"
  },
  {
    "imgUrl": "https://my.ispl-t10.com/assets/img/media/paper104.png",
    "altText": "Kesari",
    "title": "Kesari",
    "date": "August 20, 2024"
  },
  {
    "imgUrl": "https://my.ispl-t10.com/assets/img/media/paper105.png",
    "altText": "Mid-Day(Gujarati)",
    "title": "Mid-Day(Gujarati)",
    "date": "August 19, 2024"
  },
  {
    "imgUrl": "https://my.ispl-t10.com/assets/img/media/paper106.png",
    "altText": "Dainik Bhaskar",
    "title": "Dainik Bhaskar",
    "date": "August 19, 2024"
  },
  {
    "imgUrl": "https://my.ispl-t10.com/assets/img/media/paper107.png",
    "altText": "Hindustan",
    "title": "Hindustan",
    "date": "August 19, 2024"
  },
  {
    "imgUrl": "https://my.ispl-t10.com/assets/img/media/paper108.png",
    "altText": "NavBharat Times",
    "title": "NavBharat Times",
    "date": "August 19, 2024"
  },
  {
    "imgUrl": "https://my.ispl-t10.com/assets/img/media/paper109.png",
    "altText": "Millenium",
    "title": "Millenium",
    "date": "August 19, 2024"
  },
  {
    "imgUrl": "https://my.ispl-t10.com/assets/img/media/paper110.png",
    "altText": "Anand Bazaar pratika",
    "title": "Anand Bazaar pratika",
    "date": "August 19, 2024"
  },
  {
    "imgUrl": "https://my.ispl-t10.com/assets/img/media/paper111.png",
    "altText": "Ei-Samay",
    "title": "Ei-Samay",
    "date": "August 19, 2024"
  },
  {
    "imgUrl": "https://my.ispl-t10.com/assets/img/media/paper112.png",
    "altText": "Telangana Today",
    "title": "Telangana Today",
    "date": "August 19, 2024"
  },
  {
    "imgUrl": "https://my.ispl-t10.com/assets/img/media/paper113.png",
    "altText": "Velugu",
    "title": "Velugu",
    "date": "August 19, 2024"
  },
  {
    "imgUrl": "https://my.ispl-t10.com/assets/img/media/paper114.png",
    "altText": "Eenadu",
    "title": "Eenadu",
    "date": "August 19, 2024"
  },
  {
    "imgUrl": "https://my.ispl-t10.com/assets/img/media/paper115.png",
    "altText": "Prahar",
    "title": "Prahar",
    "date": "August 19, 2024"
  },
  {
    "imgUrl": "https://my.ispl-t10.com/assets/img/media/paper116.png",
    "altText": "Punyanagari",
    "title": "Punyanagari",
    "date": "August 19, 2024"
  },
  {
    "imgUrl": "https://my.ispl-t10.com/assets/img/media/paper117.png",
    "altText": "Mumbai Samachar",
    "title": "Mumbai Samachar",
    "date": "August 19, 2024"
  },
  {
    "imgUrl": "https://my.ispl-t10.com/assets/img/media/paper118.png",
    "altText": "The Pioneer",
    "title": "The Pioneer",
    "date": "August 19, 2024"
  },
  {
    "imgUrl": "https://my.ispl-t10.com/assets/img/media/paper119.png",
    "altText": "Aaj kal",
    "title": "Aaj Kal",
    "date": "August 19, 2024"
  },
  {
    "imgUrl": "https://my.ispl-t10.com/assets/img/media/paper120.png",
    "altText": "Dainik Navshakti",
    "title": "Dainik Navshakti",
    "date": "August 19, 2024"
  },
  {
    "imgUrl": "https://my.ispl-t10.com/assets/img/media/paper121.png",
    "altText": "Humara Mahanagar",
    "title": "Humara Mahanagar",
    "date": "August 19, 2024"
  },
  {
    "imgUrl": "https://my.ispl-t10.com/assets/img/media/paper122.png",
    "altText": "Apla Samraj",
    "title": "Apla Samraj",
    "date": "August 19, 2024"
  },
  {
    "imgUrl": "https://my.ispl-t10.com/assets/img/media/paper123.png",
    "altText": "Tarun Mitra",
    "title": "Tarun Mitra",
    "date": "August 19, 2024"
  }
]
